bfx/__init__.py
bfx/blosum/src/blosum/__init__.py
bfx/blosum/src/blosum/_blosum.py
bfx/blosum/src/blosum/_data.py
bfx/fastq/src/fastq/__init__.py
bfx/fastq/src/fastq/_fastq.py
bfx/fastq/src/fastq/_reader.py
bfx/fastq/src/fastq/_writer.py
bfx/miniFasta/src/miniFasta/__init__.py
bfx/miniFasta/src/miniFasta/_miniFasta.py
bfx/miniFasta/src/miniFasta/_reader.py
bfx/miniFasta/src/miniFasta/_writer.py
bfx/tajimas_d/src/tajimas_d/__init__.py
bfx/tajimas_d/src/tajimas_d/_tajimas_d.py
bfx-0.2.0.dist-info/LICENSE.txt
bfx-0.2.0.dist-info/METADATA
bfx-0.2.0.dist-info/WHEEL
bfx-0.2.0.dist-info/top_level.txt
bfx-0.2.0.dist-info/RECORD
