Metadata-Version: 2.1
Name: bfx
Version: 0.2.0
Summary: A suite for bioinformatics tools with little to no dependencies.
Home-page: https://github.com/not-a-feature/bfx
Author: Jules Kreuer
Author-email: contact@juleskreuer.eu
License: GPL-3.0-or-later
Project-URL: Documentation, https://bfx.readthedocs.io
Project-URL: Source, https://github.com/not-a-feature/bfx
Project-URL: Changelog, https://pyscaffold.org/en/latest/changelog.html
Project-URL: Tracker, https://github.com/pyscaffold/pyscaffold/issues
Project-URL: Download, https://pypi.org/project/bfx/#files
Platform: any
Classifier: Development Status :: 4 - Beta
Classifier: Programming Language :: Python
Requires-Python: >=3.8
License-File: LICENSE.txt
Requires-Dist: importlib-metadata ; python_version < "3.8"
Provides-Extra: testing
Requires-Dist: setuptools ; extra == 'testing'
Requires-Dist: pytest ; extra == 'testing'
Requires-Dist: pytest-cov ; extra == 'testing'
